zeroconf/__init__.py
zeroconf/_cache.pxd
zeroconf/_cache.py
zeroconf/_core.py
zeroconf/_dns.pxd
zeroconf/_dns.py
zeroconf/_engine.py
zeroconf/_exceptions.py
zeroconf/_handlers/__init__.py
zeroconf/_handlers/answers.pxd
zeroconf/_handlers/answers.py
zeroconf/_handlers/multicast_outgoing_queue.pxd
zeroconf/_handlers/multicast_outgoing_queue.py
zeroconf/_handlers/query_handler.pxd
zeroconf/_handlers/query_handler.py
zeroconf/_handlers/record_manager.pxd
zeroconf/_handlers/record_manager.py
zeroconf/_history.pxd
zeroconf/_history.py
zeroconf/_listener.pxd
zeroconf/_listener.py
zeroconf/_logger.py
zeroconf/_protocol/__init__.py
zeroconf/_protocol/incoming.pxd
zeroconf/_protocol/incoming.py
zeroconf/_protocol/outgoing.pxd
zeroconf/_protocol/outgoing.py
zeroconf/_record_update.pxd
zeroconf/_record_update.py
zeroconf/_services/__init__.pxd
zeroconf/_services/__init__.py
zeroconf/_services/browser.pxd
zeroconf/_services/browser.py
zeroconf/_services/info.pxd
zeroconf/_services/info.py
zeroconf/_services/registry.pxd
zeroconf/_services/registry.py
zeroconf/_services/types.py
zeroconf/_transport.py
zeroconf/_updates.pxd
zeroconf/_updates.py
zeroconf/_utils/__init__.py
zeroconf/_utils/asyncio.py
zeroconf/_utils/ipaddress.pxd
zeroconf/_utils/ipaddress.py
zeroconf/_utils/name.py
zeroconf/_utils/net.py
zeroconf/_utils/time.pxd
zeroconf/_utils/time.py
zeroconf/asyncio.py
zeroconf/const.py
zeroconf/py.typed
zeroconf/_cache.cpython-313-x86_64-linux-gnu.so
zeroconf/_dns.cpython-313-x86_64-linux-gnu.so
zeroconf/_handlers/answers.cpython-313-x86_64-linux-gnu.so
zeroconf/_handlers/multicast_outgoing_queue.cpython-313-x86_64-linux-gnu.so
zeroconf/_handlers/query_handler.cpython-313-x86_64-linux-gnu.so
zeroconf/_handlers/record_manager.cpython-313-x86_64-linux-gnu.so
zeroconf/_history.cpython-313-x86_64-linux-gnu.so
zeroconf/_listener.cpython-313-x86_64-linux-gnu.so
zeroconf/_protocol/incoming.cpython-313-x86_64-linux-gnu.so
zeroconf/_protocol/outgoing.cpython-313-x86_64-linux-gnu.so
zeroconf-0.147.1.dist-info/COPYING
zeroconf-0.147.1.dist-info/METADATA
zeroconf-0.147.1.dist-info/WHEEL
zeroconf-0.147.1.dist-info/RECORD
