Metadata-Version: 2.3
Name: zeroconf
Version: 0.147.1
Summary: A pure python implementation of multicast DNS service discovery
License: LGPL-2.1-or-later
Author: Paul Scott-Murphy
Requires-Python: >=3.9,<4.0
Classifier: Development Status :: 5 - Production/Stable
Classifier: Intended Audience :: Developers
Classifier: Intended Audience :: System Administrators
Classifier: License :: OSI Approved
Classifier: Operating System :: MacOS :: MacOS X
Classifier: Operating System :: POSIX
Classifier: Operating System :: POSIX :: Linux
Classifier: Programming Language :: Python :: 3
Classifier: Programming Language :: Python :: 3.9
Classifier: Programming Language :: Python :: 3.10
Classifier: Programming Language :: Python :: 3.11
Classifier: Programming Language :: Python :: 3.12
Classifier: Programming Language :: Python :: 3.13
Classifier: Programming Language :: Python :: Implementation :: CPython
Classifier: Programming Language :: Python :: Implementation :: PyPy
Classifier: Topic :: Software Development :: Libraries
Requires-Dist: ifaddr (>=0.1.7)
Project-URL: Bug Tracker, https://github.com/python-zeroconf/python-zeroconf/issues
Project-URL: Changelog, https://github.com/python-zeroconf/python-zeroconf/blob/master/CHANGELOG.md
Project-URL: Documentation, https://python-zeroconf.readthedocs.io
Project-URL: Repository, https://github.com/python-zeroconf/python-zeroconf
